{
  "annotations": {
    "list": [
      {
        "builtIn": 1,
        "datasource": {
          "type": "datasource",
          "uid": "grafana"
        },
        "enable": true,
        "hide": true,
        "iconColor": "rgba(0, 211, 255, 1)",
        "name": "Annotations & Alerts",
        "target": {
          "limit": 100,
          "matchAny": false,
          "tags": [],
          "type": "dashboard"
        },
        "type": "dashboard"
      }
    ]
  },
  "editable": true,
  "fiscalYearStartMonth": 0,
  "graphTooltip": 0,
  "id": 5,
  "links": [],
  "liveNow": false,
  "panels": [
    {
      "datasource": {
        "type": "prometheus",
        "uid": "prometheus"
      },
      "fieldConfig": {
        "defaults": {
          "color": {
            "mode": "thresholds"
          },
          "mappings": [],
          "thresholds": {
            "mode": "absolute",
            "steps": [
              {
                "color": "blue",
                "value": null
              }
            ]
          }
        },
        "overrides": []
      },
      "gridPos": {
        "h": 8,
        "w": 6,
        "x": 0,
        "y": 0
      },
      "id": 13,
      "options": {
        "colorMode": "value",
        "graphMode": "none",
        "justifyMode": "center",
        "orientation": "auto",
        "reduceOptions": {
          "calcs": ["sum"],
          "fields": "",
          "values": false
        },
        "text": {},
        "textMode": "auto"
      },
      "pluginVersion": "9.5.2",
      "targets": [
        {
          "datasource": {
            "type": "prometheus",
            "uid": "PBFA97CFB590B2093"
          },
          "editorMode": "code",
          "expr": "sum without (messaging_type) (rate(sqs_extensions_messaging_successes{app=~\"[[app]]\"}[$interval])*100)",
          "range": true,
          "refId": "A"
        }
      ],
      "title": "Total successful messages ",
      "type": "stat"
    },
    {
      "datasource": {
        "type": "prometheus",
        "uid": "prometheus"
      },
      "description": "",
      "fieldConfig": {
        "defaults": {
          "color": {
            "mode": "continuous-GrYlRd"
          },
          "mappings": [],
          "min": 0,
          "thresholds": {
            "mode": "absolute",
            "steps": [
              {
                "color": "green",
                "value": null
              },
              {
                "color": "yellow",
                "value": 10
              },
              {
                "color": "red",
                "value": 40
              }
            ]
          }
        },
        "overrides": []
      },
      "gridPos": {
        "h": 8,
        "w": 6,
        "x": 6,
        "y": 0
      },
      "id": 11,
      "options": {
        "colorMode": "value",
        "graphMode": "none",
        "justifyMode": "auto",
        "orientation": "auto",
        "reduceOptions": {
          "calcs": ["mean"],
          "fields": "",
          "values": false
        },
        "text": {},
        "textMode": "auto"
      },
      "pluginVersion": "9.5.2",
      "targets": [
        {
          "datasource": {
            "type": "prometheus",
            "uid": "PBFA97CFB590B2093"
          },
          "editorMode": "code",
          "expr": "rate(sqs_extensions_messaging_failures{app=~\"[[app]]\"}[$interval])*100",
          "range": true,
          "refId": "A"
        }
      ],
      "title": "Average error msg ",
      "type": "stat"
    },
    {
      "datasource": {
        "type": "prometheus",
        "uid": "prometheus"
      },
      "description": "",
      "fieldConfig": {
        "defaults": {
          "color": {
            "mode": "thresholds"
          },
          "mappings": [],
          "min": 0,
          "thresholds": {
            "mode": "percentage",
            "steps": [
              {
                "color": "green",
                "value": null
              }
            ]
          }
        },
        "overrides": [
          {
            "matcher": {
              "id": "byRegexp",
              "options": "(?:\\w+)"
            },
            "properties": [
              {
                "id": "displayName",
                "value": "$1"
              }
            ]
          }
        ]
      },
      "gridPos": {
        "h": 8,
        "w": 6,
        "x": 12,
        "y": 0
      },
      "id": 6,
      "options": {
        "colorMode": "value",
        "graphMode": "none",
        "justifyMode": "center",
        "orientation": "auto",
        "reduceOptions": {
          "calcs": ["sum"],
          "fields": "",
          "values": false
        },
        "text": {},
        "textMode": "value"
      },
      "pluginVersion": "9.5.2",
      "targets": [
        {
          "datasource": {
            "type": "prometheus",
            "uid": "PBFA97CFB590B2093"
          },
          "editorMode": "code",
          "expr": "rate(sqs_extensions_messaging_deleted{app=~\"[[app]]\"}[$interval])*100",
          "interval": "",
          "legendFormat": "{{sqs_extensions_message_type}}",
          "range": true,
          "refId": "A"
        }
      ],
      "title": "Messages deleted",
      "type": "stat"
    },
    {
      "datasource": {
        "type": "prometheus",
        "uid": "prometheus"
      },
      "fieldConfig": {
        "defaults": {
          "color": {
            "mode": "thresholds"
          },
          "mappings": [],
          "min": 0,
          "thresholds": {
            "mode": "percentage",
            "steps": [
              {
                "color": "green",
                "value": null
              }
            ]
          }
        },
        "overrides": []
      },
      "gridPos": {
        "h": 8,
        "w": 6,
        "x": 18,
        "y": 0
      },
      "id": 8,
      "options": {
        "colorMode": "value",
        "graphMode": "none",
        "justifyMode": "center",
        "orientation": "auto",
        "reduceOptions": {
          "calcs": ["mean"],
          "fields": "",
          "values": false
        },
        "text": {},
        "textMode": "auto"
      },
      "pluginVersion": "9.5.2",
      "targets": [
        {
          "datasource": {
            "type": "prometheus",
            "uid": "PBFA97CFB590B2093"
          },
          "editorMode": "code",
          "expr": "rate(sqs_extensions_messaging_successes{app=~\"[[app]]\"}[$interval])*100",
          "range": true,
          "refId": "A"
        }
      ],
      "title": "Average msg ",
      "type": "stat"
    },
    {
      "datasource": {
        "type": "prometheus",
        "uid": "prometheus"
      },
      "fieldConfig": {
        "defaults": {
          "color": {
            "mode": "palette-classic"
          },
          "custom": {
            "axisCenteredZero": false,
            "axisColorMode": "text",
            "axisLabel": "",
            "axisPlacement": "auto",
            "barAlignment": 0,
            "drawStyle": "line",
            "fillOpacity": 10,
            "gradientMode": "none",
            "hideFrom": {
              "legend": false,
              "tooltip": false,
              "viz": false
            },
            "lineInterpolation": "linear",
            "lineWidth": 1,
            "pointSize": 5,
            "scaleDistribution": {
              "type": "linear"
            },
            "showPoints": "never",
            "spanNulls": false,
            "stacking": {
              "group": "A",
              "mode": "none"
            },
            "thresholdsStyle": {
              "mode": "off"
            }
          },
          "mappings": [],
          "thresholds": {
            "mode": "absolute",
            "steps": [
              {
                "color": "green",
                "value": null
              }
            ]
          },
          "unit": "short"
        },
        "overrides": []
      },
      "gridPos": {
        "h": 9,
        "w": 12,
        "x": 0,
        "y": 8
      },
      "id": 4,
      "options": {
        "legend": {
          "calcs": [],
          "displayMode": "list",
          "placement": "bottom",
          "showLegend": true
        },
        "tooltip": {
          "mode": "multi",
          "sort": "none"
        }
      },
      "pluginVersion": "9.0.1",
      "targets": [
        {
          "datasource": {
            "type": "prometheus",
            "uid": "PBFA97CFB590B2093"
          },
          "editorMode": "code",
          "expr": "rate(sqs_extensions_messaging_successes{app=~\"[[app]]\"}[$interval])*100",
          "range": true,
          "refId": "A"
        }
      ],
      "title": "Processed messages",
      "type": "timeseries"
    },
    {
      "datasource": {
        "type": "prometheus",
        "uid": "prometheus"
      },
      "fieldConfig": {
        "defaults": {
          "color": {
            "mode": "palette-classic"
          },
          "custom": {
            "axisCenteredZero": false,
            "axisColorMode": "text",
            "axisLabel": "",
            "axisPlacement": "auto",
            "barAlignment": 0,
            "drawStyle": "line",
            "fillOpacity": 10,
            "gradientMode": "none",
            "hideFrom": {
              "legend": false,
              "tooltip": false,
              "viz": false
            },
            "lineInterpolation": "linear",
            "lineWidth": 1,
            "pointSize": 5,
            "scaleDistribution": {
              "type": "linear"
            },
            "showPoints": "never",
            "spanNulls": false,
            "stacking": {
              "group": "A",
              "mode": "none"
            },
            "thresholdsStyle": {
              "mode": "off"
            }
          },
          "mappings": [],
          "thresholds": {
            "mode": "absolute",
            "steps": [
              {
                "color": "green",
                "value": null
              },
              {
                "color": "red",
                "value": 80
              }
            ]
          },
          "unit": "short"
        },
        "overrides": []
      },
      "gridPos": {
        "h": 9,
        "w": 12,
        "x": 12,
        "y": 8
      },
      "id": 2,
      "options": {
        "legend": {
          "calcs": [],
          "displayMode": "list",
          "placement": "bottom",
          "showLegend": true
        },
        "tooltip": {
          "mode": "multi",
          "sort": "none"
        }
      },
      "pluginVersion": "9.0.1",
      "targets": [
        {
          "datasource": {
            "type": "prometheus",
            "uid": "PBFA97CFB590B2093"
          },
          "editorMode": "code",
          "expr": "rate(sqs_extensions_messaging_fetches{app=~\"[[app]]\"}[$interval])*100",
          "range": true,
          "refId": "A"
        }
      ],
      "title": "Fetched messages",
      "type": "timeseries"
    },
    {
      "datasource": {
        "type": "prometheus",
        "uid": "prometheus"
      },
      "fieldConfig": {
        "defaults": {
          "color": {
            "mode": "palette-classic"
          },
          "custom": {
            "axisCenteredZero": false,
            "axisColorMode": "text",
            "axisLabel": "",
            "axisPlacement": "auto",
            "barAlignment": 0,
            "drawStyle": "line",
            "fillOpacity": 60,
            "gradientMode": "opacity",
            "hideFrom": {
              "legend": false,
              "tooltip": false,
              "viz": false
            },
            "lineInterpolation": "linear",
            "lineWidth": 2,
            "pointSize": 5,
            "scaleDistribution": {
              "type": "linear"
            },
            "showPoints": "never",
            "spanNulls": false,
            "stacking": {
              "group": "A",
              "mode": "none"
            },
            "thresholdsStyle": {
              "mode": "line+area"
            }
          },
          "mappings": [],
          "thresholds": {
            "mode": "absolute",
            "steps": [
              {
                "color": "transparent",
                "value": null
              },
              {
                "color": "orange",
                "value": 5
              },
              {
                "color": "red",
                "value": 10
              }
            ]
          },
          "unit": "short"
        },
        "overrides": [
          {
            "matcher": {
              "id": "byName",
              "options": "Time"
            },
            "properties": [
              {
                "id": "links"
              }
            ]
          }
        ]
      },
      "gridPos": {
        "h": 14,
        "w": 24,
        "x": 0,
        "y": 17
      },
      "id": 10,
      "options": {
        "legend": {
          "calcs": [],
          "displayMode": "list",
          "placement": "bottom",
          "showLegend": true
        },
        "tooltip": {
          "mode": "multi",
          "sort": "none"
        }
      },
      "pluginVersion": "9.0.1",
      "targets": [
        {
          "datasource": {
            "type": "prometheus",
            "uid": "PBFA97CFB590B2093"
          },
          "editorMode": "code",
          "expr": "rate(sqs_extensions_messaging_failures{app=~\"[[app]]\"}[$interval]) * 100",
          "range": true,
          "refId": "A"
        }
      ],
      "title": "Failed messages",
      "type": "timeseries"
    }
  ],
  "refresh": false,
  "schemaVersion": 38,
  "style": "dark",
  "tags": [],
  "templating": {
    "list": [
      {
        "current": {
          "selected": true,
          "text": [
          ],
          "value": [
          ]
        },
        "datasource": {
          "type": "prometheus",
          "uid": "prometheus"
        },
        "definition": "label_values(app)",
        "hide": 0,
        "includeAll": false,
        "label": "Application",
        "multi": true,
        "name": "app",
        "options": [],
        "query": {
          "query": "label_values(app)",
          "refId": "PrometheusVariableQueryEditor-VariableQuery"
        },
        "refresh": 1,
        "regex": "",
        "skipUrlSync": false,
        "sort": 0,
        "type": "query"
      },
      {
        "auto": true,
        "auto_count": 30,
        "auto_min": "10s",
        "current": {
          "selected": false,
          "text": "auto",
          "value": "$__auto_interval_interval"
        },
        "hide": 0,
        "label": "Interval",
        "name": "interval",
        "options": [
          {
            "selected": true,
            "text": "auto",
            "value": "$__auto_interval_interval"
          },
          {
            "selected": false,
            "text": "30s",
            "value": "30s"
          },
          {
            "selected": false,
            "text": "1m",
            "value": "1m"
          },
          {
            "selected": false,
            "text": "5m",
            "value": "5m"
          },
          {
            "selected": false,
            "text": "10m",
            "value": "10m"
          },
          {
            "selected": false,
            "text": "30m",
            "value": "30m"
          },
          {
            "selected": false,
            "text": "1h",
            "value": "1h"
          },
          {
            "selected": false,
            "text": "6h",
            "value": "6h"
          },
          {
            "selected": false,
            "text": "12h",
            "value": "12h"
          },
          {
            "selected": false,
            "text": "1d",
            "value": "1d"
          },
          {
            "selected": false,
            "text": "7d",
            "value": "7d"
          },
          {
            "selected": false,
            "text": "14d",
            "value": "14d"
          },
          {
            "selected": false,
            "text": "30d",
            "value": "30d"
          }
        ],
        "query": "30s,1m,5m,10m,30m,1h,6h,12h,1d,7d,14d,30d",
        "queryValue": "",
        "refresh": 2,
        "skipUrlSync": false,
        "type": "interval"
      }
    ]
  },
  "time": {
    "from": "2023-08-19T08:31:49.450Z",
    "to": "2023-08-19T10:09:01.708Z"
  },
  "timepicker": {},
  "timezone": "",
  "title": "SQS.Extensions",
  "uid": "KPsYLIhnu",
  "version": 13,
  "weekStart": ""
}
